{
  "mode": "scoring",
  "teams": [
    {
      "id": "team-1",
      "name": "第 1 桌",
      "count": 0,
      "scoreCount": 19,
      "target": 10,
      "testLightSeq": 12,
      "testLightMode": "classic",
      "testLightColorIndex": 0,
      "testLightBrightness": 220,
      "testLightFinalMin": 0,
      "testLightFinalMax": 225,
      "testLightFinalPeriodMs": 9000,
      "deviceId": "esp32-table-1",
      "deviceLastSeenAt": 1776504523559,
      "clientLastSeenAt": 1776489655818,
      "updatedAt": 1776504523559
    },
    {
      "id": "team-2",
      "name": "第 2 桌",
      "count": 0,
      "scoreCount": 0,
      "target": 13,
      "testLightSeq": 0,
      "testLightMode": "classic",
      "testLightColorIndex": 0,
      "testLightBrightness": 220,
      "testLightFinalMin": 0,
      "testLightFinalMax": 225,
      "testLightFinalPeriodMs": 9000,
      "deviceId": "esp32-table-2",
      "deviceLastSeenAt": 1776487908145,
      "clientLastSeenAt": 1776487907309,
      "updatedAt": 1776489312411
    },
    {
      "id": "team-3",
      "name": "第 3 桌",
      "count": 0,
      "scoreCount": 0,
      "target": 15,
      "testLightSeq": 0,
      "testLightMode": "classic",
      "testLightColorIndex": 0,
      "testLightBrightness": 220,
      "testLightFinalMin": 0,
      "testLightFinalMax": 225,
      "testLightFinalPeriodMs": 9000,
      "deviceId": "esp32-table-3",
      "deviceLastSeenAt": 1776488210326,
      "clientLastSeenAt": 1776488071998,
      "updatedAt": 1776489312411
    },
    {
      "id": "team-4",
      "name": "第 4 桌",
      "count": 0,
      "scoreCount": 0,
      "target": 14,
      "testLightSeq": 0,
      "testLightMode": "classic",
      "testLightColorIndex": 0,
      "testLightBrightness": 220,
      "testLightFinalMin": 0,
      "testLightFinalMax": 225,
      "testLightFinalPeriodMs": 9000,
      "deviceId": "esp32-table-4",
      "deviceLastSeenAt": 1776488328945,
      "clientLastSeenAt": 1776488312642,
      "updatedAt": 1776489312411
    },
    {
      "id": "team-5",
      "name": "第 5 桌",
      "count": 0,
      "scoreCount": 0,
      "target": 15,
      "testLightSeq": 0,
      "testLightMode": "classic",
      "testLightColorIndex": 0,
      "testLightBrightness": 220,
      "testLightFinalMin": 0,
      "testLightFinalMax": 225,
      "testLightFinalPeriodMs": 9000,
      "deviceId": "esp32-table-5",
      "deviceLastSeenAt": 1776488390635,
      "clientLastSeenAt": 1776488389499,
      "updatedAt": 1776489312411
    },
    {
      "id": "team-6",
      "name": "第 6 桌",
      "count": 0,
      "scoreCount": 0,
      "target": 13,
      "testLightSeq": 0,
      "testLightMode": "classic",
      "testLightColorIndex": 0,
      "testLightBrightness": 220,
      "testLightFinalMin": 0,
      "testLightFinalMax": 225,
      "testLightFinalPeriodMs": 9000,
      "deviceId": "esp32-table-6",
      "deviceLastSeenAt": 1776488461362,
      "clientLastSeenAt": 1776488460634,
      "updatedAt": 1776489312411
    },
    {
      "id": "team-7",
      "name": "第 7 桌",
      "count": 0,
      "scoreCount": 0,
      "target": 12,
      "testLightSeq": 0,
      "testLightMode": "classic",
      "testLightColorIndex": 0,
      "testLightBrightness": 220,
      "testLightFinalMin": 0,
      "testLightFinalMax": 225,
      "testLightFinalPeriodMs": 9000,
      "deviceId": "esp32-table-7",
      "deviceLastSeenAt": 1776488612218,
      "clientLastSeenAt": 1776488594718,
      "updatedAt": 1776489312411
    },
    {
      "id": "team-8",
      "name": "第 8 桌",
      "count": 0,
      "scoreCount": 0,
      "target": 15,
      "testLightSeq": 0,
      "testLightMode": "classic",
      "testLightColorIndex": 0,
      "testLightBrightness": 220,
      "testLightFinalMin": 0,
      "testLightFinalMax": 225,
      "testLightFinalPeriodMs": 9000,
      "deviceId": "esp32-table-8",
      "deviceLastSeenAt": 1776488725395,
      "clientLastSeenAt": 1776488719740,
      "updatedAt": 1776489312411
    },
    {
      "id": "team-9",
      "name": "第 9 桌",
      "count": 0,
      "scoreCount": 0,
      "target": 11,
      "testLightSeq": 0,
      "testLightMode": "classic",
      "testLightColorIndex": 0,
      "testLightBrightness": 220,
      "testLightFinalMin": 0,
      "testLightFinalMax": 225,
      "testLightFinalPeriodMs": 9000,
      "deviceId": "esp32-table-9",
      "deviceLastSeenAt": 1776488806470,
      "clientLastSeenAt": 1776488795869,
      "updatedAt": 1776489312411
    },
    {
      "id": "team-10",
      "name": "第 10 桌",
      "count": 0,
      "scoreCount": 0,
      "target": 13,
      "testLightSeq": 0,
      "testLightMode": "classic",
      "testLightColorIndex": 0,
      "testLightBrightness": 220,
      "testLightFinalMin": 0,
      "testLightFinalMax": 225,
      "testLightFinalPeriodMs": 9000,
      "deviceId": "esp32-table-10",
      "deviceLastSeenAt": 1776488893885,
      "clientLastSeenAt": 1776488881285,
      "updatedAt": 1776489312411
    },
    {
      "id": "team-11",
      "name": "第 11 桌",
      "count": 0,
      "scoreCount": 0,
      "target": 12,
      "testLightSeq": 0,
      "testLightMode": "classic",
      "testLightColorIndex": 0,
      "testLightBrightness": 220,
      "testLightFinalMin": 0,
      "testLightFinalMax": 225,
      "testLightFinalPeriodMs": 9000,
      "deviceId": "",
      "deviceLastSeenAt": 0,
      "clientLastSeenAt": 0,
      "updatedAt": 1776489312411
    },
    {
      "id": "team-12",
      "name": "第 12 桌",
      "count": 0,
      "scoreCount": 0,
      "target": 11,
      "testLightSeq": 0,
      "testLightMode": "classic",
      "testLightColorIndex": 0,
      "testLightBrightness": 220,
      "testLightFinalMin": 0,
      "testLightFinalMax": 225,
      "testLightFinalPeriodMs": 9000,
      "deviceId": "",
      "deviceLastSeenAt": 0,
      "clientLastSeenAt": 0,
      "updatedAt": 1776489312411
    },
    {
      "id": "team-13",
      "name": "第 13 桌",
      "count": 0,
      "scoreCount": 0,
      "target": 12,
      "testLightSeq": 0,
      "testLightMode": "classic",
      "testLightColorIndex": 0,
      "testLightBrightness": 220,
      "testLightFinalMin": 0,
      "testLightFinalMax": 225,
      "testLightFinalPeriodMs": 9000,
      "deviceId": "",
      "deviceLastSeenAt": 0,
      "clientLastSeenAt": 0,
      "updatedAt": 1776489312411
    },
    {
      "id": "team-14",
      "name": "第 14 桌",
      "count": 0,
      "scoreCount": 0,
      "target": 13,
      "testLightSeq": 0,
      "testLightMode": "classic",
      "testLightColorIndex": 0,
      "testLightBrightness": 220,
      "testLightFinalMin": 0,
      "testLightFinalMax": 225,
      "testLightFinalPeriodMs": 9000,
      "deviceId": "",
      "deviceLastSeenAt": 0,
      "clientLastSeenAt": 0,
      "updatedAt": 1776489312411
    },
    {
      "id": "team-15",
      "name": "第 15 桌",
      "count": 0,
      "scoreCount": 0,
      "target": 14,
      "testLightSeq": 0,
      "testLightMode": "classic",
      "testLightColorIndex": 0,
      "testLightBrightness": 220,
      "testLightFinalMin": 0,
      "testLightFinalMax": 225,
      "testLightFinalPeriodMs": 9000,
      "deviceId": "",
      "deviceLastSeenAt": 0,
      "clientLastSeenAt": 0,
      "updatedAt": 1776489312411
    },
    {
      "id": "team-16",
      "name": "第 16 桌",
      "count": 0,
      "scoreCount": 0,
      "target": 12,
      "testLightSeq": 0,
      "testLightMode": "classic",
      "testLightColorIndex": 0,
      "testLightBrightness": 220,
      "testLightFinalMin": 0,
      "testLightFinalMax": 225,
      "testLightFinalPeriodMs": 9000,
      "deviceId": "",
      "deviceLastSeenAt": 0,
      "clientLastSeenAt": 0,
      "updatedAt": 1776489312411
    },
    {
      "id": "team-17",
      "name": "第 17 桌",
      "count": 0,
      "scoreCount": 0,
      "target": 14,
      "testLightSeq": 0,
      "testLightMode": "classic",
      "testLightColorIndex": 0,
      "testLightBrightness": 220,
      "testLightFinalMin": 0,
      "testLightFinalMax": 225,
      "testLightFinalPeriodMs": 9000,
      "deviceId": "esp32-C8936314",
      "deviceLastSeenAt": 1776487823862,
      "clientLastSeenAt": 1776487207085,
      "updatedAt": 1776489312411
    },
    {
      "id": "team-18",
      "name": "第 18 桌",
      "count": 0,
      "scoreCount": 0,
      "target": 13,
      "testLightSeq": 0,
      "testLightMode": "classic",
      "testLightColorIndex": 0,
      "testLightBrightness": 220,
      "testLightFinalMin": 0,
      "testLightFinalMax": 225,
      "testLightFinalPeriodMs": 9000,
      "deviceId": "",
      "deviceLastSeenAt": 0,
      "clientLastSeenAt": 0,
      "updatedAt": 1776489312411
    },
    {
      "id": "team-19",
      "name": "第 19 桌",
      "count": 0,
      "scoreCount": 0,
      "target": 14,
      "testLightSeq": 0,
      "testLightMode": "classic",
      "testLightColorIndex": 0,
      "testLightBrightness": 220,
      "testLightFinalMin": 0,
      "testLightFinalMax": 225,
      "testLightFinalPeriodMs": 9000,
      "deviceId": "",
      "deviceLastSeenAt": 0,
      "clientLastSeenAt": 0,
      "updatedAt": 1776489312411
    },
    {
      "id": "team-20",
      "name": "第 20 桌",
      "count": 0,
      "scoreCount": 0,
      "target": 13,
      "testLightSeq": 0,
      "testLightMode": "classic",
      "testLightColorIndex": 0,
      "testLightBrightness": 220,
      "testLightFinalMin": 0,
      "testLightFinalMax": 225,
      "testLightFinalPeriodMs": 9000,
      "deviceId": "",
      "deviceLastSeenAt": 0,
      "clientLastSeenAt": 0,
      "updatedAt": 1776489312411
    }
  ]
}